timol/R_hemo.xyz
timol/__init__.py
timol/custom_typing.py
timol/main.py
timol/reader.py
timol/sidebar.py
timol/test_xyz.xyz
timol/timol.tcss
timol/ui.py
timol/utils.py
timol/viewer.py
timol/cli/__init__.py
timol/cli/bmark.py
timol/cli/main.py
timol-1.2.3.dist-info/METADATA
timol-1.2.3.dist-info/WHEEL
timol-1.2.3.dist-info/entry_points.txt
timol-1.2.3.dist-info/licenses/LICENSE
timol-1.2.3.dist-info/RECORD
