Metadata-Version: 2.4
Name: timol
Version: 1.2.3
Summary: 3D Molecular viewer in the terminal
Author-email: GregoryFonseca <gregorycordeirofonseca@gmail.com>
License-Expression: MIT
License-File: LICENSE
Requires-Python: >=3.9
Requires-Dist: ase>=3.24.0
Requires-Dist: importlib-metadata>=8.7.0
Requires-Dist: importlib-resources>=6.5.2
Requires-Dist: numpy>=2.0.2
Requires-Dist: scikit-image>=0.24.0
Requires-Dist: textual>=3.2.0
Requires-Dist: tqdm>=4.67.1
